jitterbug
