Metadata-Version: 2.1
Name: jitterbug
Version: 0.1.1
Summary: 'Test the stability of multithreaded code by adding random delays'
Home-page: https://github.com/MarkCBell/jitterbug
Author: Mark Bell
Author-email: mcbell@illinois.edu
License: UNKNOWN
Keywords: testing,multithreaded,parallel,fuzzing
Platform: UNKNOWN
Classifier: Development Status :: 3 - Alpha
Classifier: Intended Audience :: Education
Classifier: Intended Audience :: Science/Research
Classifier: Natural Language :: English
Classifier: Operating System :: OS Independent
Classifier: Programming Language :: Python
Classifier: Topic :: Software Development :: Testing
Requires-Python: >=3.8
